README
setup.py
dinospeak/__init__.py
dinospeak/dinospeak.py
dinospeak/test.py
dinospeak.egg-info/PKG-INFO
dinospeak.egg-info/SOURCES.txt
dinospeak.egg-info/dependency_links.txt
dinospeak.egg-info/not-zip-safe
dinospeak.egg-info/requires.txt
dinospeak.egg-info/top_level.txt