Metadata-Version: 1.0
Name: dinospeak
Version: 0.1.1
Summary: Dinosaur language translation library
Home-page: UNKNOWN
Author: Dimitris Glezos
Author-email: glezos@indifex.com
License: UNKNOWN
Platform: UNKNOWN
